sigc/__init__.py
sigc/core.py
sigc/resources/KEGG_metabolism_nc.gmt
sigc/resources/REACTOME_metabolism.gmt
sigc-0.1.18.dist-info/LICENSE
sigc-0.1.18.dist-info/METADATA
sigc-0.1.18.dist-info/WHEEL
sigc-0.1.18.dist-info/top_level.txt
sigc-0.1.18.dist-info/RECORD
