Metadata-Version: 2.1
Name: sigc
Version: 0.1.18
Summary: gene signature score for gene expression matrix
Home-page: https://github.com/seqyuan/sigc
Author: Zan Yuan
Author-email: yfinddream@gmail.com
Classifier: Programming Language :: Python :: 3
Classifier: License :: OSI Approved :: MIT License
Classifier: Operating System :: OS Independent
License-File: LICENSE
Requires-Dist: pyscenic
Requires-Dist: ctxcore
Requires-Dist: GSVA
